py_swf/__init__.py
py_swf/config_definitions.py
py_swf/errors.py
py_swf/clients/__init__.py
py_swf/clients/activity_task.py
py_swf/clients/admin.py
py_swf/clients/decision.py
py_swf/clients/workflow.py
py_swf-1.3.0.dist-info/DESCRIPTION.rst
py_swf-1.3.0.dist-info/METADATA
py_swf-1.3.0.dist-info/RECORD
py_swf-1.3.0.dist-info/WHEEL
py_swf-1.3.0.dist-info/metadata.json
py_swf-1.3.0.dist-info/top_level.txt
