Metadata-Version: 2.0
Name: py-swf
Version: 1.3.0
Summary: A SWF client library that makes things easy for building workflow logic
Home-page: http://py-swf.readthedocs.io/en/latest/
Author: Henri Bai
Author-email: hbai@yelp.com
License: UNKNOWN
Keywords: py_swf,swf,amazon,workflow
Platform: UNKNOWN
Classifier: Development Status :: 5 - Production/Stable
Classifier: Intended Audience :: Developers
Classifier: Natural Language :: English
Classifier: Programming Language :: Python :: 2
Classifier: Programming Language :: Python :: 2.7
Classifier: Programming Language :: Python :: 3
Classifier: Programming Language :: Python :: 3.4
Classifier: Programming Language :: Python :: Implementation :: PyPy
Requires-Dist: boto3
Requires-Dist: botocore (>=1.3.24)
